README.rst
setup.py
PyFDP/FDP.py
PyFDP/__init__.py
PyFDP/rekFDP.py
PyFDP/volFDP.py
PyFDP.egg-info/PKG-INFO
PyFDP.egg-info/SOURCES.txt
PyFDP.egg-info/dependency_links.txt
PyFDP.egg-info/not-zip-safe
PyFDP.egg-info/top_level.txt