Metadata-Version: 1.1
Name: PyFDP
Version: 1.1
Summary: FDP (Fast Debug Protocol) : KD client for debugging Windows VM without /DEBUG enabled.
Home-page: https://winbagility.github.io
Author: UNKNOWN
Author-email: UNKNOWN
License: UNKNOWN
Platform: UNKNOWN
Classifier: Programming Language :: Python :: 2
Classifier: Programming Language :: Python :: 3
Classifier: Operating System :: Microsoft :: Windows
Classifier: Topic :: Software Development :: Debuggers
Provides: PyFDP
